{
    "fromFiles": [
        "C:\\Users\\billy\\AppData\\Roaming\\Adobe\\After Effects\\17.5\\aeks\\billy_key_ae.txt",
		"G:\\document\\Adobe\\Premiere Pro\\14.0\\Profile-billy\\Win\\billy_pr.kys",
		"C:\\Users\\billy\\AppData\\Roaming\\Adobe\\Audition\\13.0\\Shortcuts\\billy.xml",
		"C:\\Users\\billy\\AppData\\Roaming\\Adobe\\Adobe Photoshop 2021\\Presets\\Keyboard Shortcuts\\billy_ps.kys",
		"C:\\Users\\billy\\AppData\\Roaming\\Adobe\\Adobe Illustrator 25 Settings\\zh_CN\\x64\\billy_ai.kys",
		"C:\\Users\\billy\\AppData\\Roaming\\Adobe\\Adobe Photoshop 2021\\Presets\\Custom Toolbars\\billy-ps-tools.tbr"
    ],
    "toDirs0": ["F:\\doc\\MachineSettings"],
    "fromDirs": [
        "D:\\Program Files\\Adobe After Effects 2020\\Support Files\\Scripts",
		"D:\\DirectRun",
        "E:\\CreateProcess",
        "E:\\YingTaoZi",
        "F:\\billy-fast",
        "F:\\billy-code",
        "F:\\billyxin-modules",
        "F:\\billyxin-works",
        "F:\\collection",
        "F:\\doc",
        "G:\\document\\Adobe\\After Effects 2020\\User Presets"
    ],
    "ignores": [".git"],
    "toDirs": ["N:\\local-a"],
    "toDirs2": ["K:\\local-b"],
    "tests": ["", ""]
}
